LICENSE
README.md
setup.py
password_generator/__init__.py
password_generator/password.py
password_generator_module.egg-info/PKG-INFO
password_generator_module.egg-info/SOURCES.txt
password_generator_module.egg-info/dependency_links.txt
password_generator_module.egg-info/top_level.txt