Metadata-Version: 2.1
Name: password-generator-module
Version: 0.3.0
Summary: Generate strong passwords quickly
Home-page: https://github.com/Mazzya/password-generator-module
Author: Mazzya
License: MIT
Keywords: python,password
Platform: UNKNOWN
Classifier: Programming Language :: Python :: 3.0
Classifier: Development Status :: 5 - Production/Stable
Classifier: License :: OSI Approved :: MIT License
Classifier: Topic :: Software Development :: Libraries :: Python Modules
Classifier: Topic :: Security
Classifier: Topic :: Software Development :: Version Control :: Git
Classifier: Operating System :: MacOS :: MacOS X
Classifier: Operating System :: Microsoft :: Windows :: Windows 10
Classifier: Operating System :: Unix
